yamltopy/__init__.py
yamltopy/yamltopy.py
yamltopy-1.0.0.dist-info/LICENSE
yamltopy-1.0.0.dist-info/METADATA
yamltopy-1.0.0.dist-info/WHEEL
yamltopy-1.0.0.dist-info/entry_points.txt
yamltopy-1.0.0.dist-info/top_level.txt
yamltopy-1.0.0.dist-info/RECORD
