Metadata-Version: 2.1
Name: yamltopy
Version: 1.0.0
Summary: A CLI tool to convert YAML file to Python module for better load performance
Home-page: https://github.com/szikszail/yamltopy
Author: Laszlo Szikszai
Author-email: sziklaszlo@gmail.com
License: UNKNOWN
Project-URL: Bug Tracker, https://github.com/szikszail/yamltopy/issues
Platform: UNKNOWN
Classifier: Programming Language :: Python :: 3
Classifier: License :: OSI Approved :: MIT License
Classifier: Operating System :: OS Independent
Requires-Python: >=3.6
